on_rails/Result.py
on_rails/ResultDetail.py
on_rails/ResultDetails/ErrorDetail.py
on_rails/ResultDetails/Errors/BadRequestError.py
on_rails/ResultDetails/Errors/ConflictError.py
on_rails/ResultDetails/Errors/ExceptionError.py
on_rails/ResultDetails/Errors/ForbiddenError.py
on_rails/ResultDetails/Errors/InternalError.py
on_rails/ResultDetails/Errors/NotFoundError.py
on_rails/ResultDetails/Errors/UnauthorizedError.py
on_rails/ResultDetails/Errors/ValidationError.py
on_rails/ResultDetails/Errors/__init__.py
on_rails/ResultDetails/Success/CreatedDetail.py
on_rails/ResultDetails/Success/NotModifiedDetail.py
on_rails/ResultDetails/Success/PartialContentDetail.py
on_rails/ResultDetails/Success/WarningDetail.py
on_rails/ResultDetails/Success/__init__.py
on_rails/ResultDetails/SuccessDetail.py
on_rails/ResultDetails/__init__.py
on_rails/__init__.py
on_rails/_utility.py
on_rails/decorator.py
on_rails/test_helpers.py
on_rails-4.2.0.dist-info/LICENSE
on_rails-4.2.0.dist-info/METADATA
on_rails-4.2.0.dist-info/WHEEL
on_rails-4.2.0.dist-info/RECORD
