Metadata-Version: 2.1
Name: on-rails
Version: 4.2.0
Summary: Simple and powerful Railway Oriented library for python
Home-page: https://github.com/Payadel/on_rails
License: GPLV3
Keywords: railway oriented,functional programming,error handling
Author: Payadel
Author-email: payadelteam@gmail.com
Requires-Python: >=3.8,<4.0
Classifier: License :: Other/Proprietary License
Classifier: Programming Language :: Python :: 3
Classifier: Programming Language :: Python :: 3.8
Classifier: Programming Language :: Python :: 3.9
Classifier: Programming Language :: Python :: 3.10
Classifier: Programming Language :: Python :: 3.11
Project-URL: Repository, https://github.com/Payadel/on_rails
